mopidy_beets/__init__.py
mopidy_beets/actor.py
mopidy_beets/client.py
mopidy_beets/ext.conf
mopidy_beets/library.py
mopidy_beets/translator.py
mopidy_beets/browsers/__init__.py
mopidy_beets/browsers/albums.py
Mopidy_Beets-4.0.1.dist-info/LICENSE
Mopidy_Beets-4.0.1.dist-info/METADATA
Mopidy_Beets-4.0.1.dist-info/WHEEL
Mopidy_Beets-4.0.1.dist-info/entry_points.txt
Mopidy_Beets-4.0.1.dist-info/top_level.txt
Mopidy_Beets-4.0.1.dist-info/RECORD
